Metadata-Version: 1.0
Name: sheba
Version: 0.0.6
Summary: Sheba SQL - SQL for normal people.
Home-page: http://github.com/davisp/sheba
Author: Paul J. Davis
Author-email: paul.joseph.davis@gmail.com
License: UNKNOWN
Platform: UNKNOWN
